topsis_101703572/__init__.py
topsis_101703572/topsis_101703572.py
topsis_101703572-4.1.0.dist-info/LICENSE
topsis_101703572-4.1.0.dist-info/METADATA
topsis_101703572-4.1.0.dist-info/WHEEL
topsis_101703572-4.1.0.dist-info/entry_points.txt
topsis_101703572-4.1.0.dist-info/top_level.txt
topsis_101703572-4.1.0.dist-info/RECORD
