Metadata-Version: 2.1
Name: topsis-101703572
Version: 4.1.0
Summary: Python package to implement TOPSIS
Home-page: https://github.com/sunvir72/Topsis
Author: Sunvir Singh
Author-email: sunvirsingh72@gmail.com
License: MIT
Platform: UNKNOWN
Classifier: License :: OSI Approved :: MIT License
Classifier: Programming Language :: Python :: 3
Classifier: Programming Language :: Python :: 3.7
